hypergen/__init__.py
hypergen/py.typed
hypergen/cli/__init__.py
hypergen/cli/main.py
hypergen/config/__init__.py
hypergen/dataset/__init__.py
hypergen/dataset/base.py
hypergen/inference/__init__.py
hypergen/model/__init__.py
hypergen/model/base.py
hypergen/optimization/__init__.py
hypergen/serve/__init__.py
hypergen/serve/api.py
hypergen/serve/queue.py
hypergen/serve/server.py
hypergen/serve/worker.py
hypergen/training/__init__.py
hypergen/training/lora.py
hypergen/utils/__init__.py
hypergen-0.1.0.dist-info/METADATA
hypergen-0.1.0.dist-info/WHEEL
hypergen-0.1.0.dist-info/entry_points.txt
hypergen-0.1.0.dist-info/licenses/LICENCE
hypergen-0.1.0.dist-info/RECORD
