Metadata-Version: 2.4
Name: hypergen
Version: 0.1.0
Summary: Optimized inference and fine-tuning framework for diffusion (image & video) models.
Project-URL: Homepage, https://github.com/ntegrals/hypergen
Project-URL: Repository, https://github.com/ntegrals/hypergen
Project-URL: Issues, https://github.com/ntegrals/hypergen/issues
Author-email: Julian Schoen <j.schoen@mail.com>
License: MIT
License-File: LICENCE
Keywords: ai,deep-learning,diffusion,flux,image-generation,lora,sdxl,stable-diffusion
Classifier: Development Status :: 3 - Alpha
Classifier: Intended Audience :: Developers
Classifier: Intended Audience :: Science/Research
Classifier: License :: OSI Approved :: MIT License
Classifier: Programming Language :: Python :: 3
Classifier: Programming Language :: Python :: 3.10
Classifier: Programming Language :: Python :: 3.11
Classifier: Programming Language :: Python :: 3.12
Classifier: Topic :: Scientific/Engineering :: Artificial Intelligence
Classifier: Topic :: Software Development :: Libraries :: Python Modules
Requires-Python: >=3.10
Requires-Dist: accelerate>=0.30.0
Requires-Dist: diffusers>=0.30.0
Requires-Dist: fastapi>=0.104.0
Requires-Dist: numpy>=1.24.0
Requires-Dist: peft>=0.8.0
Requires-Dist: pillow>=10.0.0
Requires-Dist: pydantic>=2.0.0
Requires-Dist: safetensors>=0.4.0
Requires-Dist: torch>=2.0.0
Requires-Dist: transformers>=4.40.0
Requires-Dist: uvicorn[standard]>=0.24.0
Provides-Extra: all
Requires-Dist: av>=12.0.0; extra == 'all'
Requires-Dist: deepspeed>=0.14.0; extra == 'all'
Requires-Dist: flash-attn>=2.5.0; extra == 'all'
Requires-Dist: opencv-python>=4.9.0; extra == 'all'
Requires-Dist: pytest-cov>=4.0.0; extra == 'all'
Requires-Dist: pytest>=7.0.0; extra == 'all'
Requires-Dist: ruff>=0.1.0; extra == 'all'
Requires-Dist: xformers>=0.0.25; extra == 'all'
Provides-Extra: deepspeed
Requires-Dist: deepspeed>=0.14.0; extra == 'deepspeed'
Provides-Extra: dev
Requires-Dist: pytest-cov>=4.0.0; extra == 'dev'
Requires-Dist: pytest>=7.0.0; extra == 'dev'
Requires-Dist: ruff>=0.1.0; extra == 'dev'
Provides-Extra: flash
Requires-Dist: flash-attn>=2.5.0; extra == 'flash'
Provides-Extra: video
Requires-Dist: av>=12.0.0; extra == 'video'
Requires-Dist: opencv-python>=4.9.0; extra == 'video'
Provides-Extra: xformers
Requires-Dist: xformers>=0.0.25; extra == 'xformers'
